{"cameraMode":{"drawMode":0,"name":"Shaded","section":"Shading Mode"},"sceneLighting":true,"audioPlay":false,"sceneViewState":{"showFog":true,"showMaterialUpdate":false,"showSkybox":true,"showFlares":true,"showImageEffects":true,"showParticleSystems":true},"in2DMode":false,"pivot":{"x":-201.76951599121095,"y":-135.60337829589845,"z":-32.41677474975586},"rotation":{"x":0.18563345074653626,"y":-0.7340677976608276,"z":0.22177347540855409,"w":0.6144529581069946},"size":265.71759033203127,"orthographic":false}